LICENSE
README.md
setup.py
pysarar/__init__.py
pysarar.egg-info/PKG-INFO
pysarar.egg-info/SOURCES.txt
pysarar.egg-info/dependency_links.txt
pysarar.egg-info/requires.txt
pysarar.egg-info/top_level.txt
pysarar/model/__init__.py
pysarar/model/sarar.py